[
	{"id":1,"title":"Haber 1","content":"Haber İçeriği","image":null,"url":"http://localhost:3000/infos/1.json"},
	{"id":2,"title":"Haber 2","content":"Haber İçeriği","image":null,"url":"http://localhost:3000/infos/1.json"},
	{"id":3,"title":"Haber 3","content":"Haber İçeriği","image":null,"url":"http://localhost:3000/infos/1.json"},
	{"id":4,"title":"Haber 4","content":"Haber İçeriği","image":null,"url":"http://localhost:3000/infos/1.json"},
	{"id":5,"title":"Haber 5","content":"Haber İçeriği","image":null,"url":"http://localhost:3000/infos/1.json"},
	{"id":6,"title":"Haber 6","content":"Haber İçeriği","image":null,"url":"http://localhost:3000/infos/1.json"}

]